setup.py
HtmlCreator/Element.py
HtmlCreator/EmptyElement.py
HtmlCreator/ExistElement.py
HtmlCreator/Html.py
HtmlCreator/__init__.py
fig_html_builder.egg-info/PKG-INFO
fig_html_builder.egg-info/SOURCES.txt
fig_html_builder.egg-info/dependency_links.txt
fig_html_builder.egg-info/entry_points.txt
fig_html_builder.egg-info/top_level.txt