Metadata-Version: 2.1
Name: fig-html-builder
Version: 0.0.1
Summary: this package is use for creating html by python
Home-page: https://normidar.com
Author: normidar
Author-email: normidar7@gmail.com
License: UNKNOWN
Platform: UNKNOWN
